INSPECT/__init__.py
INSPECT/inspector.py
INSPECT/utils.py
hpc_inspect/__init__.py
hpc_inspect/inspector.py
hpc_inspect/utils.py
hpc_inspect-0.1.dist-info/LICENSE
hpc_inspect-0.1.dist-info/METADATA
hpc_inspect-0.1.dist-info/WHEEL
hpc_inspect-0.1.dist-info/entry_points.txt
hpc_inspect-0.1.dist-info/top_level.txt
hpc_inspect-0.1.dist-info/RECORD
