Metadata-Version: 2.1
Name: hpc-inspect
Version: 0.1
Summary: Intra Node Stencil Performance Evaluation Collection
Home-page: https://github.com/RRZE-HPC/INSPECT
Author: Julian Hammer
Author-email: julian.hammer@fau.de
License: AGPLv3
Keywords: hpc performance benchmark analysis
Platform: UNKNOWN
Classifier: Development Status :: 3 - Alpha
Classifier: Intended Audience :: Developers
Classifier: Intended Audience :: Science/Research
Classifier: Topic :: Scientific/Engineering
Classifier: Topic :: Software Development
Classifier: Topic :: Utilities
Classifier: License :: OSI Approved :: GNU Affero General Public License v3
Classifier: Programming Language :: Python :: 3
Classifier: Programming Language :: Python :: 3.5
Classifier: Programming Language :: Python :: 3.6
Classifier: Programming Language :: Python :: 3.7
Requires-Python: >=3.5
Requires-Dist: kerncraft
Requires-Dist: pandas
Requires-Dist: compress-pickle
Requires-Dist: jupyter
Requires-Dist: matplotlib
